napari_rioxarray/__init__.py
napari_rioxarray/_reader.py
napari_rioxarray/napari.yaml
napari_rioxarray/_tests/__init__.py
napari_rioxarray/_tests/test_reader.py
napari_rioxarray/_tests/data/S2A_MSIL1C_20170102T111442_N0204_R137_T30TXT_20170102T111441_TCI_cloudoptimized_512_200m.tif
napari_rioxarray/_tests/data/__init__.py
napari_rioxarray-0.0.1.dist-info/LICENSE
napari_rioxarray-0.0.1.dist-info/METADATA
napari_rioxarray-0.0.1.dist-info/WHEEL
napari_rioxarray-0.0.1.dist-info/entry_points.txt
napari_rioxarray-0.0.1.dist-info/top_level.txt
napari_rioxarray-0.0.1.dist-info/RECORD
