Metadata-Version: 2.1
Name: napari-rioxarray
Version: 0.0.1
Summary: A rioxarray plugin for napari supporting GDAL raster datatypes
Home-page: https://github.com/AndrewAnnex/napari-rioxarray
Author: Dr. Andrew Annex
Author-email: ama6fy@virginia.edu
License: BSD-3-Clause
Project-URL: Bug Tracker, https://github.com/AndrewAnnex/napari-rioxarray/issues
Project-URL: Documentation, https://github.com/AndrewAnnex/napari-rioxarray#README.md
Project-URL: Source Code, https://github.com/AndrewAnnex/napari-rioxarray
Project-URL: User Support, https://github.com/AndrewAnnex/napari-rioxarray/issues
Classifier: Development Status :: 2 - Pre-Alpha
Classifier: Framework :: napari
Classifier: Intended Audience :: Developers
Classifier: License :: OSI Approved :: BSD License
Classifier: Operating System :: OS Independent
Classifier: Programming Language :: Python
Classifier: Programming Language :: Python :: 3
Classifier: Programming Language :: Python :: 3 :: Only
Classifier: Programming Language :: Python :: 3.8
Classifier: Programming Language :: Python :: 3.9
Classifier: Programming Language :: Python :: 3.10
Classifier: Topic :: Scientific/Engineering :: Image Processing
Requires-Python: >=3.8
License-File: LICENSE
Requires-Dist: numpy
Requires-Dist: napari
Requires-Dist: rioxarray
Provides-Extra: testing
Requires-Dist: tox ; extra == 'testing'
Requires-Dist: pytest ; extra == 'testing'
Requires-Dist: pytest-cov ; extra == 'testing'
